MANIFEST.in
README.rst
edit_pip_configuration.py
package_info.py
setup.py
nvidia_pyindex/__init__.py
nvidia_pyindex/cmdline.py
nvidia_pyindex/utils.py
nvidia_pyindex.egg-info/PKG-INFO
nvidia_pyindex.egg-info/SOURCES.txt
nvidia_pyindex.egg-info/dependency_links.txt
nvidia_pyindex.egg-info/entry_points.txt
nvidia_pyindex.egg-info/top_level.txt