Metadata-Version: 1.2
Name: nvidia-pyindex
Version: 1.0.8
Summary: A tool that adds the NVIDIA PIP Index to the environment.
Home-page: http://www.nvidia.com/
Author: Jonathan Dekhtiar
Author-email: jdekhtiar@nvidia.com
Maintainer: Jonathan Dekhtiar
Maintainer-email: jdekhtiar@nvidia.com
License: Apache2
Download-URL: http://www.nvidia.com/
Keywords: nvidia,deep learning,machine learning,supervised learning,unsupervised learning,reinforcement learning,logging
Platform: Linux
Classifier: Development Status :: 3 - Alpha
Classifier: Intended Audience :: Developers
Classifier: Intended Audience :: Science/Research
Classifier: Intended Audience :: Information Technology
Classifier: Topic :: Scientific/Engineering
Classifier: Topic :: Scientific/Engineering :: Image Recognition
Classifier: Topic :: Scientific/Engineering :: Artificial Intelligence
Classifier: Topic :: Software Development :: Libraries
Classifier: Topic :: Utilities
Classifier: License :: OSI Approved :: Apache Software License
Classifier: Programming Language :: Python :: 3
Classifier: Programming Language :: Python :: 3.6
Classifier: Programming Language :: Python :: 3.7
Classifier: Programming Language :: Python :: 3.8
Classifier: Environment :: Console
Classifier: Natural Language :: English
Classifier: Operating System :: OS Independent
